vyvert/__init__.py
vyvert/datastructures.py
vyvert/utils.py
vyvert-0.1.0.dist-info/METADATA
vyvert-0.1.0.dist-info/WHEEL
vyvert-0.1.0.dist-info/RECORD
