Metadata-Version: 2.1
Name: vyvert
Version: 0.1.0
Summary: VyVeRT is an dependency injection library inspored by pytest and FastAPI
Author: Mike Oz
Author-email: kozloffsky@hotmail.com
Requires-Python: >=3.9,<4.0
Classifier: Programming Language :: Python :: 3
Classifier: Programming Language :: Python :: 3.9
Classifier: Programming Language :: Python :: 3.10
Classifier: Programming Language :: Python :: 3.11
Classifier: Programming Language :: Python :: 3.12
Requires-Dist: anyio (>=4.3.0,<5.0.0)
